grpc_csds/__init__.py
grpcio_csds-1.76.0.dist-info/LICENSE
grpcio_csds-1.76.0.dist-info/METADATA
grpcio_csds-1.76.0.dist-info/WHEEL
grpcio_csds-1.76.0.dist-info/top_level.txt
grpcio_csds-1.76.0.dist-info/RECORD
