Metadata-Version: 2.1
Name: grpcio-csds
Version: 1.76.0
Summary: xDS configuration dump library
Home-page: https://grpc.io
Author: The gRPC Authors
Author-email: grpc-io@googlegroups.com
License: Apache License 2.0
Classifier: Development Status :: 5 - Production/Stable
Classifier: Programming Language :: Python
Classifier: Programming Language :: Python :: 3
Classifier: License :: OSI Approved :: Apache Software License
Requires-Python: >=3.9
License-File: LICENSE
Requires-Dist: protobuf <7.0.0,>=6.31.1
Requires-Dist: xds-protos ==1.76.0
Requires-Dist: grpcio >=1.76.0
